l2tscaffolder/.style.ts.yapf
l2tscaffolder/.style.yapf
l2tscaffolder/__init__.py
l2tscaffolder/definitions/__init__.py
l2tscaffolder/definitions/interface.py
l2tscaffolder/definitions/manager.py
l2tscaffolder/definitions/plaso.py
l2tscaffolder/definitions/timesketch.py
l2tscaffolder/definitions/turbinia.py
l2tscaffolder/frontend/__init__.py
l2tscaffolder/frontend/cli_output_handler.py
l2tscaffolder/frontend/frontend.py
l2tscaffolder/frontend/output_handler.py
l2tscaffolder/helpers/__init__.py
l2tscaffolder/helpers/cli.py
l2tscaffolder/helpers/git.py
l2tscaffolder/lib/__init__.py
l2tscaffolder/lib/code_formatter.py
l2tscaffolder/lib/definitions.py
l2tscaffolder/lib/engine.py
l2tscaffolder/lib/errors.py
l2tscaffolder/lib/file_handler.py
l2tscaffolder/lib/mapping_helper.py
l2tscaffolder/scaffolders/__init__.py
l2tscaffolder/scaffolders/interface.py
l2tscaffolder/scaffolders/manager.py
l2tscaffolder/scaffolders/plaso.py
l2tscaffolder/scaffolders/plaso_sqlite.py
l2tscaffolder/scaffolders/timesketch.py
l2tscaffolder/scaffolders/timesketch_index.py
l2tscaffolder/scaffolders/timesketch_sketch.py
l2tscaffolder/scaffolders/turbinia.py
l2tscaffolder/templates/__init__.py
l2tscaffolder/templates/sqlite_plugin.jinja2
l2tscaffolder/templates/sqlite_plugin_formatter.jinja2
l2tscaffolder/templates/sqlite_plugin_formatter_test.jinja2
l2tscaffolder/templates/sqlite_plugin_test.jinja2
l2tscaffolder/templates/ts_index_analyzer.jinja2
l2tscaffolder/templates/ts_index_analyzer_test.jinja2
l2tscaffolder/templates/ts_sketch_analyzer.jinja2
l2tscaffolder/templates/ts_sketch_analyzer_test.jinja2
l2tscaffolder/templates/turbinia_job.jinja2
l2tscaffolder/templates/turbinia_task.jinja2
l2tscaffolder-20191010.data/data/sqlite_plugin.jinja2
l2tscaffolder-20191010.data/data/sqlite_plugin_formatter.jinja2
l2tscaffolder-20191010.data/data/sqlite_plugin_formatter_test.jinja2
l2tscaffolder-20191010.data/data/sqlite_plugin_test.jinja2
l2tscaffolder-20191010.data/data/ts_index_analyzer.jinja2
l2tscaffolder-20191010.dist-info/LICENSE
l2tscaffolder-20191010.dist-info/METADATA
l2tscaffolder-20191010.dist-info/WHEEL
l2tscaffolder-20191010.dist-info/top_level.txt
l2tscaffolder-20191010.dist-info/RECORD
