Metadata-Version: 2.1
Name: l2tscaffolder
Version: 20191010
Summary: Scaffolder project for l2t, helping to bootstrap l2t development.
Home-page: https://github.com/log2timeline/l2tscaffolder
Maintainer: Log2Timeline maintainers
Maintainer-email: log2timeline-maintainers@googlegroups.com
License: Apache License, Version 2.0
Keywords: plaso l2t scaffolder log2timeline turbinia timesketch
Platform: UNKNOWN
Classifier: Development Status :: 4 - Beta
Classifier: Environment :: Console
Classifier: Operating System :: OS Independent
Classifier: Programming Language :: Python
Requires-Python: >=3
Requires-Dist: Click (>=6.7)
Requires-Dist: setuptools (>=35.0.2)
Requires-Dist: jinja2 (>=2.9.6)
Requires-Dist: colorama (>=0.3.7)
Requires-Dist: yapf (==0.22)
Requires-Dist: pexpect (>=4.2.1)
